pyudemy/__init__.py
pyudemy/udemy.py
pyudemy-1.1.0.dist-info/LICENSE
pyudemy-1.1.0.dist-info/METADATA
pyudemy-1.1.0.dist-info/WHEEL
pyudemy-1.1.0.dist-info/RECORD
