Metadata-Version: 2.1
Name: pyudemy
Version: 1.1.0
Summary: Simple integrate of API udemy.com with python
Home-page: https://github.com/hudsonbrendon/pyudemy#readme
License: MIT
Author: Hudson Brendon
Author-email: contato.hudsonbrendon@gmail.com
Requires-Python: >=3.8,<4.0
Classifier: License :: OSI Approved :: MIT License
Classifier: Programming Language :: Python :: 3
Classifier: Programming Language :: Python :: 3.8
Classifier: Programming Language :: Python :: 3.9
Classifier: Programming Language :: Python :: 3.10
Classifier: Programming Language :: Python :: 3.11
Classifier: Programming Language :: Python :: 3.12
Requires-Dist: requests (>=2.28.1,<3.0.0)
Project-URL: Repository, https://github.com/hudsonbrendon/pyudemy
